finbright_technical/__init__.py
finbright_technical/technical.py
finbright_technical-0.0.1.dist-info/METADATA
finbright_technical-0.0.1.dist-info/WHEEL
finbright_technical-0.0.1.dist-info/licenses/LICENSE
finbright_technical-0.0.1.dist-info/RECORD
