Metadata-Version: 2.1
Name: finbright_technical
Version: 0.0.1
Summary: finbright private utils package
Author-email: Sarah KhorashadiZadeh <sara.khorashadi@yahoo.com>
License-File: LICENSE
Classifier: License :: OSI Approved :: MIT License
Classifier: Operating System :: OS Independent
Classifier: Programming Language :: Python :: 3
Requires-Python: >=3.7
Requires-Dist: finta
Requires-Dist: pandas
